request5.py
request5-0.0.2.dist-info/METADATA
request5-0.0.2.dist-info/WHEEL
request5-0.0.2.dist-info/entry_points.txt
request5-0.0.2.dist-info/top_level.txt
request5-0.0.2.dist-info/RECORD
