Metadata-Version: 2.1
Name: request5
Version: 0.0.2
Summary: Enjoy!
Home-page: https://github.com/H454NSec
Author: H454NSec
Author-email: mrhasan660066@gmail.com
License: UNKNOWN
Platform: UNKNOWN
Classifier: License :: OSI Approved :: MIT License
Classifier: Programming Language :: Python :: 3
Classifier: Programming Language :: Python :: 3.6
Classifier: Programming Language :: Python :: 3.7
Classifier: Programming Language :: Python :: 3.8
Classifier: Programming Language :: Python :: 3.9
